{
	"type": "",
	"parts": [{
		"id": 1,
		"bodyPart": "全身",
		"name": "有氧",
		"imageUrl": "image/bodyparts/aerobic.png",
		"description": "",
		"predefined": true,
		"actionSet": [{
			"id": 1,
			"name": "慢跑",
			"equipment": "",
			"description": "",
			"imageUrl": "image/actions/aerobic/canter.png",
			"predefined": true,
			"partSet": ["全身"],
			"defaultQuantity": {
				"gpQuantity": 1,
				"quantity": 30,
				"weight": 5
			},
			"selected": false,
			"gpMeasurement": "分钟",
			"measurement": "Km"
		},
		{
			"id": 2,
			"name": "原地跑步",
			"equipment": "",
			"description": "",
			"imageUrl": "image/actions/aerobic/running_on_the_spot.png",
			"predefined": true,
			"partSet": ["全身"],
			"defaultQuantity": {
				"gpQuantity": 1,
				"quantity": 30,
				"weight": 100
			},
			"selected": false,
			"gpMeasurement": "分钟",
			"measurement": "次"
		},
		{
			"id": 3,
			"name": "原地高抬腿",
			"equipment": "",
			"description": "",
			"imageUrl": "image/actions/aerobic/place_high_leg_on_the_spot.png",
			"predefined": true,
			"partSet": ["全身"],
			"defaultQuantity": {
				"gpQuantity": 6,
				"quantity": 10,
				"weight": 100
			},
			"selected": false,
			"gpMeasurement": "分钟",
			"measurement": "次"
		},
		{
			"id": 4,
			"name": "快走",
			"equipment": "",
			"description": "",
			"imageUrl": "image/actions/aerobic/fast_walking.png",
			"predefined": true,
			"partSet": ["全身"],
			"defaultQuantity": {
				"gpQuantity": 1,
				"quantity": 30,
				"weight": 3
			},
			"selected": false,
			"gpMeasurement": "分钟",
			"measurement": "Km"
		},
		{
			"id": 5,
			"name": "椭圆机",
			"equipment": "",
			"description": "",
			"imageUrl": "image/actions/aerobic/elliptical_machine.png",
			"predefined": true,
			"partSet": ["全身"],
			"defaultQuantity": {
				"gpQuantity": 1,
				"quantity": 30,
				"weight": 3
			},
			"selected": false,
			"gpMeasurement": "分钟",
			"measurement": "Km"
		},
		{
			"id": 6,
			"name": "开合跳",
			"equipment": "",
			"description": "",
			"imageUrl": "image/actions/aerobic/jumping_jacks.png",
			"predefined": true,
			"partSet": ["全身"],
			"defaultQuantity": {
				"gpQuantity": 6,
				"quantity": 10,
				"weight": 100
			},
			"selected": false,
			"gpMeasurement": "分钟",
			"measurement": "次"
		},
		{
			"id": 7,
			"name": "动感单车",
			"equipment": "",
			"description": "",
			"imageUrl": "image/actions/aerobic/spinning.png",
			"predefined": true,
			"partSet": ["全身"],
			"defaultQuantity": {
				"gpQuantity": 1,
				"quantity": 30,
				"weight": 8
			},
			"selected": false,
			"gpMeasurement": "分钟",
			"measurement": "Km"
		},
		{
			"id": 8,
			"name": "登山机",
			"equipment": "",
			"description": "",
			"imageUrl": "image/actions/aerobic/climbing.png",
			"predefined": true,
			"partSet": ["全身"],
			"defaultQuantity": {
				"gpQuantity": 1,
				"quantity": 30,
				"weight": 5
			},
			"selected": false,
			"gpMeasurement": "分钟",
			"measurement": "Km"
		},
		{
			"id": 9,
			"name": "跳绳",
			"equipment": "",
			"description": "",
			"imageUrl": "image/actions/aerobic/rope_skipping.png",
			"predefined": true,
			"partSet": ["全身"],
			"defaultQuantity": {
				"gpQuantity": 6,
				"quantity": 3,
				"weight": 50
			},
			"selected": false,
			"gpMeasurement": "分钟",
			"measurement": "个"
		},
		{
			"id": 10,
			"name": "俯身登山",
			"equipment": "",
			"description": "",
			"imageUrl": "image/actions/aerobic/bend_over_climbing.png",
			"predefined": true,
			"partSet": ["全身"],
			"defaultQuantity": {
				"gpQuantity": 6,
				"quantity": 5,
				"weight": 50
			},
			"selected": false,
			"gpMeasurement": "分钟",
			"measurement": "个"
		},
		{
			"id": 11,
			"name": "自定义动作",
			"equipment": "",
			"description": "",
			"imageUrl": "image/plus_64px1.png",
			"predefined": true,
			"partSet": ["全身"],
			"defaultQuantity": {
				
			},
			"selected": false
		}],
		"selected": false
	},
	{
		"id": 2,
		"bodyPart": "胸部",
		"name": "胸上部",
		"imageUrl": "image/bodyparts/chest.png",
		"description": "",
		"predefined": true,
		"actionSet": [{
			"id": 1,
			"name": "上斜杠铃推举",
			"equipment": "",
			"description": "",
			"imageUrl": "image/actions/chest/horizontal_barbell_bench_press.png",
			"predefined": true,
			"partSet": ["胸部"],
			"defaultQuantity": {
				"gpQuantity": 6,
				"quantity": 10,
				"weight": 30
			},
			"selected": false,
			"gpMeasurement": "次",
			"measurement": "Kg"
		},
		{
			"id": 2,
			"name": "上斜哑铃推举",
			"equipment": "",
			"description": "",
			"imageUrl": "image/actions/chest/incline_dumbbell_bench_press.png",
			"predefined": true,
			"partSet": ["胸部"],
			"defaultQuantity": {
				"gpQuantity": 6,
				"quantity": 10,
				"weight": 20
			},
			"selected": false,
			"gpMeasurement": "次",
			"measurement": "Kg"
		},
		{
			"id": 3,
			"name": "上斜器械推举",
			"equipment": "",
			"description": "",
			"imageUrl": "image/actions/chest/incline_machine_press.png",
			"predefined": true,
			"partSet": ["胸部"],
			"defaultQuantity": {
				"gpQuantity": 6,
				"quantity": 10,
				"weight": 30
			},
			"selected": false,
			"gpMeasurement": "次",
			"measurement": "Kg"
		},
		{
			"id": 4,
			"name": "下斜钻石俯卧撑",
			"equipment": "",
			"description": "",
			"imageUrl": "image/actions/chest/down_incline_diamond_push_up.png",
			"predefined": true,
			"partSet": ["胸部"],
			"defaultQuantity": {
				"gpQuantity": 6,
				"quantity": 10,
				"weight": 0
			},
			"selected": false,
			"gpMeasurement": "次",
			"measurement": "Kg"
		},
		{
			"id": 5,
			"name": "上斜哑铃飞鸟",
			"equipment": "",
			"description": "",
			"imageUrl": "image/actions/chest/incline_dumbbell_bench_fly.png",
			"predefined": true,
			"partSet": ["胸部"],
			"defaultQuantity": {
				"gpQuantity": 6,
				"quantity": 10,
				"weight": 20
			},
			"selected": false,
			"gpMeasurement": "次",
			"measurement": "Kg"
		},
		{
			"id": 6,
			"name": "上斜拉索夹胸",
			"equipment": "",
			"description": "",
			"imageUrl": "image/actions/chest/incline_able_crossover.png",
			"predefined": true,
			"partSet": ["胸部"],
			"defaultQuantity": {
				"gpQuantity": 6,
				"quantity": 10,
				"weight": 30
			},
			"selected": false,
			"gpMeasurement": "次",
			"measurement": "Kg"
		}],
		"selected": false
	},
	{
		"id": 3,
		"bodyPart": "胸部",
		"name": "胸中部",
		"imageUrl": "image/bodyparts/chest.png",
		"description": "",
		"predefined": true,
		"actionSet": [{
			"id": 1,
			"name": "平板杠铃卧推",
			"equipment": "",
			"description": "",
			"imageUrl": "image/actions/chest/horizontal_barbell_bench_press.png",
			"predefined": true,
			"partSet": ["胸部"],
			"defaultQuantity": {
				"gpQuantity": 6,
				"quantity": 10,
				"weight": 30
			},
			"selected": false,
			"gpMeasurement": "次",
			"measurement": "Kg"
		},
		{
			"id": 2,
			"name": "平板哑铃卧推",
			"equipment": "",
			"description": "",
			"imageUrl": "image/actions/chest/horizontal_dumbbell_bench_press.png",
			"predefined": true,
			"partSet": ["胸部"],
			"defaultQuantity": {
				"gpQuantity": 6,
				"quantity": 10,
				"weight": 20
			},
			"selected": false,
			"gpMeasurement": "次",
			"measurement": "Kg"
		},
		{
			"id": 3,
			"name": "坐姿器械推胸",
			"equipment": "",
			"description": "",
			"imageUrl": "image/actions/chest/seated_machine_press.png",
			"predefined": true,
			"partSet": ["胸部"],
			"defaultQuantity": {
				"gpQuantity": 6,
				"quantity": 10,
				"weight": 30
			},
			"selected": false,
			"gpMeasurement": "次",
			"measurement": "Kg"
		},
		{
			"id": 4,
			"name": "标准俯卧撑",
			"equipment": "",
			"description": "",
			"imageUrl": "image/actions/chest/stand_push_up.png",
			"predefined": true,
			"partSet": ["胸部"],
			"defaultQuantity": {
				"gpQuantity": 6,
				"quantity": 10,
				"weight": 0
			},
			"selected": false,
			"gpMeasurement": "次",
			"measurement": "Kg"
		},
		{
			"id": 5,
			"name": "跪姿俯卧撑",
			"equipment": "",
			"description": "",
			"imageUrl": "image/actions/chest/kneel_push_up.png",
			"predefined": true,
			"partSet": ["胸部"],
			"defaultQuantity": {
				"gpQuantity": 6,
				"quantity": 10,
				"weight": 0
			},
			"selected": false,
			"gpMeasurement": "次",
			"measurement": "Kg"
		},
		{
			"id": 6,
			"name": "平板哑铃飞鸟",
			"equipment": "",
			"description": "",
			"imageUrl": "image/actions/chest/horizontal_dumbbell_bench_fly.png",
			"predefined": true,
			"partSet": ["胸部"],
			"defaultQuantity": {
				"gpQuantity": 6,
				"quantity": 10,
				"weight": 30
			},
			"selected": false,
			"gpMeasurement": "次",
			"measurement": "Kg"
		},
		{
			"id": 7,
			"name": "蝴蝶机器械夹胸",
			"equipment": "",
			"description": "",
			"imageUrl": "image/actions/chest/butterfly_machine_crossover.png",
			"predefined": true,
			"partSet": ["胸部"],
			"defaultQuantity": {
				"gpQuantity": 6,
				"quantity": 10,
				"weight": 30
			},
			"selected": false,
			"gpMeasurement": "次",
			"measurement": "Kg"
		},
		{
			"id": 8,
			"name": "拉力器十字夹胸",
			"equipment": "",
			"description": "",
			"imageUrl": "image/actions/chest/cable_crossover.png",
			"predefined": true,
			"partSet": ["胸部"],
			"defaultQuantity": {
				"gpQuantity": 6,
				"quantity": 10,
				"weight": 30
			},
			"selected": false,
			"gpMeasurement": "次",
			"measurement": "Kg"
		}],
		"selected": false
	},
	{
		"id": 4,
		"bodyPart": "胸部",
		"name": "胸下部",
		"imageUrl": "image/bodyparts/chest.png",
		"description": "",
		"predefined": true,
		"actionSet": [{
			"id": 1,
			"name": "下斜杠铃推举",
			"equipment": "",
			"description": "",
			"imageUrl": "image/actions/chest/horizontal_barbell_bench_press.png",
			"predefined": true,
			"partSet": ["胸部"],
			"defaultQuantity": {
				"gpQuantity": 6,
				"quantity": 10,
				"weight": 30
			},
			"selected": false,
			"gpMeasurement": "次",
			"measurement": "Kg"
		},
		{
			"id": 2,
			"name": "下斜哑铃推举",
			"equipment": "",
			"description": "",
			"imageUrl": "image/actions/chest/horizontal_dumbbell_bench_press.png",
			"predefined": true,
			"partSet": ["胸部"],
			"defaultQuantity": {
				"gpQuantity": 6,
				"quantity": 10,
				"weight": 20
			},
			"selected": false,
			"gpMeasurement": "次",
			"measurement": "Kg"
		},
		{
			"id": 3,
			"name": "双杠臂屈伸",
			"equipment": "",
			"description": "",
			"imageUrl": "image/actions/chest/dip_on_parallel_bars.png",
			"predefined": true,
			"partSet": ["胸部"],
			"defaultQuantity": {
				"gpQuantity": 6,
				"quantity": 10,
				"weight": 0
			},
			"selected": false,
			"gpMeasurement": "次",
			"measurement": "Kg"
		},
		{
			"id": 4,
			"name": "上斜宽距俯卧撑",
			"equipment": "",
			"description": "",
			"imageUrl": "image/actions/chest/incline_wide_push_up.png",
			"predefined": true,
			"partSet": ["胸部"],
			"defaultQuantity": {
				"gpQuantity": 6,
				"quantity": 10,
				"weight": 0
			},
			"selected": false,
			"gpMeasurement": "次",
			"measurement": "Kg"
		},
		{
			"id": 5,
			"name": "下斜拉索夹胸",
			"equipment": "",
			"description": "",
			"imageUrl": "image/actions/chest/decline_cable_crossover.png",
			"predefined": true,
			"partSet": ["胸部"],
			"defaultQuantity": {
				"gpQuantity": 6,
				"quantity": 10,
				"weight": 30
			},
			"selected": false,
			"gpMeasurement": "次",
			"measurement": "Kg"
		},
		{
			"id": 6,
			"name": "自定义动作",
			"equipment": "",
			"description": "",
			"imageUrl": "image/plus_64px1.png",
			"predefined": true,
			"partSet": ["胸部"],
			"defaultQuantity": {
				
			},
			"selected": false
		}],
		"selected": false
	},
	{
		"id": 5,
		"bodyPart": "肩部",
		"name": "前束",
		"imageUrl": "image/bodyparts/shoulder.png",
		"description": "",
		"predefined": true,
		"actionSet": [{
			"id": 1,
			"name": "颈前杠铃推举",
			"equipment": "",
			"description": "",
			"imageUrl": "image/actions/shoulder/bar_military_press.png",
			"predefined": true,
			"partSet": ["肩部"],
			"defaultQuantity": {
				"gpQuantity": 6,
				"quantity": 10,
				"weight": 30
			},
			"selected": false,
			"gpMeasurement": "次",
			"measurement": "Kg"
		},
		{
			"id": 2,
			"name": "站姿哑单臂铃前平举",
			"equipment": "",
			"description": "",
			"imageUrl": "image/actions/shoulder/standing_one_arm_dumbbell_front_press.png",
			"predefined": true,
			"partSet": ["肩部"],
			"defaultQuantity": {
				"gpQuantity": 6,
				"quantity": 10,
				"weight": 10
			},
			"selected": false,
			"gpMeasurement": "次",
			"measurement": "Kg"
		},
		{
			"id": 3,
			"name": "站姿哑铃前平举",
			"equipment": "",
			"description": "",
			"imageUrl": "image/actions/shoulder/standing_dumbbells_front_press.png",
			"predefined": true,
			"partSet": ["肩部"],
			"defaultQuantity": {
				"gpQuantity": 6,
				"quantity": 10,
				"weight": 10
			},
			"selected": false,
			"gpMeasurement": "次",
			"measurement": "Kg"
		}],
		"selected": false
	},
	{
		"id": 6,
		"bodyPart": "肩部",
		"name": "中束",
		"imageUrl": "image/bodyparts/shoulder.png",
		"description": "",
		"predefined": true,
		"actionSet": [{
			"id": 1,
			"name": "器械推举",
			"equipment": "",
			"description": "",
			"imageUrl": "image/actions/shoulder/machine_press.png",
			"predefined": true,
			"partSet": ["肩部"],
			"defaultQuantity": {
				"gpQuantity": 6,
				"quantity": 10,
				"weight": 20
			},
			"selected": false,
			"gpMeasurement": "次",
			"measurement": "Kg"
		},
		{
			"id": 2,
			"name": "坐姿哑铃推举",
			"equipment": "",
			"description": "",
			"imageUrl": "image/actions/shoulder/seated_dumbbell_press.png",
			"predefined": true,
			"partSet": ["肩部"],
			"defaultQuantity": {
				"gpQuantity": 6,
				"quantity": 10,
				"weight": 20
			},
			"selected": false,
			"gpMeasurement": "次",
			"measurement": "Kg"
		},
		{
			"id": 3,
			"name": "站姿哑铃推举",
			"equipment": "",
			"description": "",
			"imageUrl": "image/actions/shoulder/standing_dumbbell_press.png",
			"predefined": true,
			"partSet": ["肩部"],
			"defaultQuantity": {
				"gpQuantity": 6,
				"quantity": 10,
				"weight": 20
			},
			"selected": false,
			"gpMeasurement": "次",
			"measurement": "Kg"
		},
		{
			"id": 4,
			"name": "站姿哑铃侧平举",
			"equipment": "",
			"description": "",
			"imageUrl": "image/actions/shoulder/standing_dumbbell_lateral_raise.png",
			"predefined": true,
			"partSet": ["肩部"],
			"defaultQuantity": {
				"gpQuantity": 6,
				"quantity": 10,
				"weight": 10
			},
			"selected": false,
			"gpMeasurement": "次",
			"measurement": "Kg"
		},
		{
			"id": 5,
			"name": "L侧平举",
			"equipment": "",
			"description": "",
			"imageUrl": "image/actions/shoulder/L_lateral_raise.png",
			"predefined": true,
			"partSet": ["肩部"],
			"defaultQuantity": {
				"gpQuantity": 6,
				"quantity": 10,
				"weight": 10
			},
			"selected": false,
			"gpMeasurement": "次",
			"measurement": "Kg"
		},
		{
			"id": 6,
			"name": "阿诺德哑铃推举",
			"equipment": "",
			"description": "",
			"imageUrl": "image/actions/shoulder/arnold_press.png",
			"predefined": true,
			"partSet": ["肩部"],
			"defaultQuantity": {
				"gpQuantity": 6,
				"quantity": 10,
				"weight": 20
			},
			"selected": false,
			"gpMeasurement": "次",
			"measurement": "Kg"
		}],
		"selected": false
	},
	{
		"id": 7,
		"bodyPart": "肩部",
		"name": "后束",
		"imageUrl": "image/bodyparts/shoulder.png",
		"description": "",
		"predefined": true,
		"actionSet": [{
			"id": 1,
			"name": "颈后杠铃推举",
			"equipment": "",
			"description": "",
			"imageUrl": "image/actions/shoulder/overhead_bar_press.png",
			"predefined": true,
			"partSet": ["肩部"],
			"defaultQuantity": {
				"gpQuantity": 6,
				"quantity": 10,
				"weight": 20
			},
			"selected": false,
			"gpMeasurement": "次",
			"measurement": "Kg"
		},
		{
			"id": 2,
			"name": "俯身拉索侧平举",
			"equipment": "",
			"description": "",
			"imageUrl": "image/actions/shoulder/cable_rear_lateral_raise.png",
			"predefined": true,
			"partSet": ["肩部"],
			"defaultQuantity": {
				"gpQuantity": 6,
				"quantity": 10,
				"weight": 10
			},
			"selected": false,
			"gpMeasurement": "次",
			"measurement": "Kg"
		},
		{
			"id": 3,
			"name": "俯身哑铃侧平举",
			"equipment": "",
			"description": "",
			"imageUrl": "image/actions/shoulder/dumbbell_rear_lateral_raise.png",
			"predefined": true,
			"partSet": ["肩部"],
			"defaultQuantity": {
				"gpQuantity": 6,
				"quantity": 10,
				"weight": 10
			},
			"selected": false,
			"gpMeasurement": "次",
			"measurement": "Kg"
		},
		{
			"id": 4,
			"name": "哑铃反向飞鸟",
			"equipment": "",
			"description": "",
			"imageUrl": "image/actions/shoulder/dumbbell_reverse_fly.png",
			"predefined": true,
			"partSet": ["肩部"],
			"defaultQuantity": {
				"gpQuantity": 6,
				"quantity": 10,
				"weight": 10
			},
			"selected": false,
			"gpMeasurement": "次",
			"measurement": "Kg"
		}],
		"selected": false
	},
	{
		"id": 8,
		"bodyPart": "肩部",
		"name": "斜方肌",
		"imageUrl": "image/bodyparts/shoulder.png",
		"description": "",
		"predefined": true,
		"actionSet": [{
			"id": 1,
			"name": "站姿耸肩",
			"equipment": "",
			"description": "",
			"imageUrl": "image/actions/shoulder/stand_shrug.png",
			"predefined": true,
			"partSet": ["肩部"],
			"defaultQuantity": {
				"gpQuantity": 6,
				"quantity": 10,
				"weight": 30
			},
			"selected": false,
			"gpMeasurement": "次",
			"measurement": "Kg"
		},
		{
			"id": 2,
			"name": "自定义动作",
			"equipment": "",
			"description": "",
			"imageUrl": "image/plus_64px1.png",
			"predefined": true,
			"partSet": ["肩部"],
			"defaultQuantity": {
				
			},
			"selected": false
		}],
		"selected": false
	},
	{
		"id": 9,
		"bodyPart": "背部",
		"name": "背部",
		"imageUrl": "image/bodyparts/back.png",
		"description": "",
		"predefined": true,
		"actionSet": [{
			"id": 1,
			"name": "反握宽距引体向上",
			"equipment": "",
			"description": "",
			"imageUrl": "image/actions/back/reverse_neutral_grip_pull_up.png",
			"predefined": true,
			"partSet": ["背部"],
			"defaultQuantity": {
				"gpQuantity": 6,
				"quantity": 10,
				"weight": 0
			},
			"selected": false,
			"gpMeasurement": "次",
			"measurement": "Kg"
		},
		{
			"id": 2,
			"name": "反握窄距引体向上",
			"equipment": "",
			"description": "",
			"imageUrl": "image/actions/back/reverse_narrow_pull_up.png",
			"predefined": true,
			"partSet": ["背部"],
			"defaultQuantity": {
				"gpQuantity": 6,
				"quantity": 10,
				"weight": 0
			},
			"selected": false,
			"gpMeasurement": "次",
			"measurement": "Kg"
		},
		{
			"id": 3,
			"name": "正握宽距引体向上",
			"equipment": "",
			"description": "",
			"imageUrl": "image/actions/back/neutral_grip_pull_up.png",
			"predefined": true,
			"partSet": ["背部"],
			"defaultQuantity": {
				"gpQuantity": 6,
				"quantity": 10,
				"weight": 0
			},
			"selected": false,
			"gpMeasurement": "次",
			"measurement": "Kg"
		},
		{
			"id": 4,
			"name": "正握窄距引体向上",
			"equipment": "",
			"description": "",
			"imageUrl": "image/actions/back/narrow_pull_up.png",
			"predefined": true,
			"partSet": ["背部"],
			"defaultQuantity": {
				"gpQuantity": 6,
				"quantity": 10,
				"weight": 0
			},
			"selected": false,
			"gpMeasurement": "次",
			"measurement": "Kg"
		},
		{
			"id": 5,
			"name": "标准高位下拉",
			"equipment": "",
			"description": "",
			"imageUrl": "image/actions/back/stand_machine_pull_up.png",
			"predefined": true,
			"partSet": ["背部"],
			"defaultQuantity": {
				"gpQuantity": 6,
				"quantity": 10,
				"weight": 30
			},
			"selected": false,
			"gpMeasurement": "次",
			"measurement": "Kg"
		},
		{
			"id": 6,
			"name": "反握高位下拉",
			"equipment": "",
			"description": "",
			"imageUrl": "image/actions/back/reverse_cable_pull_up.png",
			"predefined": true,
			"partSet": ["背部"],
			"defaultQuantity": {
				"gpQuantity": 6,
				"quantity": 10,
				"weight": 30
			},
			"selected": false,
			"gpMeasurement": "次",
			"measurement": "Kg"
		},
		{
			"id": 7,
			"name": "器械反握下拉",
			"equipment": "",
			"description": "",
			"imageUrl": "image/actions/back/reverse_machine_pull_up.png",
			"predefined": true,
			"partSet": ["背部"],
			"defaultQuantity": {
				"gpQuantity": 6,
				"quantity": 10,
				"weight": 30
			},
			"selected": false,
			"gpMeasurement": "次",
			"measurement": "Kg"
		},
		{
			"id": 8,
			"name": "反向器械飞鸟",
			"equipment": "",
			"description": "",
			"imageUrl": "image/actions/back/reverse_machine_fly.png",
			"predefined": true,
			"partSet": ["背部"],
			"defaultQuantity": {
				"gpQuantity": 6,
				"quantity": 10,
				"weight": 30
			},
			"selected": false,
			"gpMeasurement": "次",
			"measurement": "Kg"
		},
		{
			"id": 9,
			"name": "俯身单臂哑铃划船",
			"equipment": "",
			"description": "",
			"imageUrl": "image/actions/back/bent_over_one_arm_row.png",
			"predefined": true,
			"partSet": ["背部"],
			"defaultQuantity": {
				"gpQuantity": 6,
				"quantity": 10,
				"weight": 20
			},
			"selected": false,
			"gpMeasurement": "次",
			"measurement": "Kg"
		},
		{
			"id": 10,
			"name": "坐姿器械对握划船",
			"equipment": "",
			"description": "",
			"imageUrl": "image/actions/back/seated_cable_close_row.png",
			"predefined": true,
			"partSet": ["背部"],
			"defaultQuantity": {
				"gpQuantity": 6,
				"quantity": 10,
				"weight": 30
			},
			"selected": false,
			"gpMeasurement": "次",
			"measurement": "Kg"
		},
		{
			"id": 11,
			"name": "俯身反握杠铃划船",
			"equipment": "",
			"description": "",
			"imageUrl": "image/actions/back/bent_over_reverse_barbell_row.png",
			"predefined": true,
			"partSet": ["背部"],
			"defaultQuantity": {
				"gpQuantity": 6,
				"quantity": 10,
				"weight": 30
			},
			"selected": false,
			"gpMeasurement": "次",
			"measurement": "Kg"
		},
		{
			"id": 12,
			"name": "俯身反握哑铃划船",
			"equipment": "",
			"description": "",
			"imageUrl": "image/actions/back/bent_over_reverse_dumbbell_row.png",
			"predefined": true,
			"partSet": ["背部"],
			"defaultQuantity": {
				"gpQuantity": 6,
				"quantity": 10,
				"weight": 30
			},
			"selected": false,
			"gpMeasurement": "次",
			"measurement": "Kg"
		},
		{
			"id": 13,
			"name": "杠铃罗马尼亚硬拉",
			"equipment": "",
			"description": "",
			"imageUrl": "image/actions/back/romanian_barbell_deadlift.png",
			"predefined": true,
			"partSet": ["背部"],
			"defaultQuantity": {
				"gpQuantity": 6,
				"quantity": 10,
				"weight": 30
			},
			"selected": false,
			"gpMeasurement": "次",
			"measurement": "Kg"
		},
		{
			"id": 14,
			"name": "杠铃直腿硬拉",
			"equipment": "",
			"description": "",
			"imageUrl": "image/actions/back/straight_leg_barbell_deadlift.png",
			"predefined": true,
			"partSet": ["背部"],
			"defaultQuantity": {
				"gpQuantity": 6,
				"quantity": 10,
				"weight": 30
			},
			"selected": false,
			"gpMeasurement": "次",
			"measurement": "Kg"
		},
		{
			"id": 15,
			"name": "自定义动作",
			"equipment": "",
			"description": "",
			"imageUrl": "image/plus_64px1.png",
			"predefined": true,
			"partSet": ["背部"],
			"defaultQuantity": {
				
			},
			"selected": false
		}],
		"selected": false
	},
	{
		"id": 10,
		"bodyPart": "腰部",
		"name": "腰部",
		"imageUrl": "image/bodyparts/waist.png",
		"description": "",
		"predefined": true,
		"actionSet": [{
			"id": 1,
			"name": "杠铃罗马尼亚硬拉",
			"equipment": "",
			"description": "",
			"imageUrl": "image/actions/waist/romanian_barbell_deadlift.png",
			"predefined": true,
			"partSet": ["腰部"],
			"defaultQuantity": {
				"gpQuantity": 6,
				"quantity": 10,
				"weight": 30
			},
			"selected": false,
			"gpMeasurement": "次",
			"measurement": "Kg"
		},
		{
			"id": 2,
			"name": "杠铃直腿硬拉",
			"equipment": "",
			"description": "",
			"imageUrl": "image/actions/waist/straight_leg_barbell_deadlift.png",
			"predefined": true,
			"partSet": ["腰部"],
			"defaultQuantity": {
				"gpQuantity": 6,
				"quantity": 10,
				"weight": 30
			},
			"selected": false,
			"gpMeasurement": "次",
			"measurement": "Kg"
		},
		{
			"id": 3,
			"name": "平板支撑",
			"equipment": "",
			"description": "",
			"imageUrl": "image/actions/waist/plank.png",
			"predefined": true,
			"partSet": ["腰部"],
			"defaultQuantity": {
				"gpQuantity": 6,
				"quantity": 10,
				"weight": 0
			},
			"selected": false,
			"gpMeasurement": "次",
			"measurement": "Kg"
		},
		{
			"id": 4,
			"name": "山羊挺身",
			"equipment": "",
			"description": "",
			"imageUrl": "image/actions/waist/back_hyperextension.png",
			"predefined": true,
			"partSet": ["腰部"],
			"defaultQuantity": {
				"gpQuantity": 6,
				"quantity": 10,
				"weight": 0
			},
			"selected": false,
			"gpMeasurement": "次",
			"measurement": "Kg"
		},
		{
			"id": 5,
			"name": "十字挺身",
			"equipment": "",
			"description": "",
			"imageUrl": "image/actions/waist/cross_lift.png",
			"predefined": true,
			"partSet": ["腰部"],
			"defaultQuantity": {
				"gpQuantity": 6,
				"quantity": 10,
				"weight": 0
			},
			"selected": false,
			"gpMeasurement": "次",
			"measurement": "Kg"
		},
		{
			"id": 6,
			"name": "自定义动作",
			"equipment": "",
			"description": "",
			"imageUrl": "image/plus_64px1.png",
			"predefined": true,
			"partSet": ["腰部"],
			"defaultQuantity": {
				
			},
			"selected": false
		}],
		"selected": false
	},
	{
		"id": 11,
		"bodyPart": "腹部",
		"name": "腹部",
		"imageUrl": "image/bodyparts/abs.png",
		"description": "",
		"predefined": true,
		"actionSet": [{
			"id": 1,
			"name": "下斜仰卧起坐",
			"equipment": "",
			"description": "",
			"imageUrl": "image/actions/abs/decline_sit_up.png",
			"predefined": true,
			"partSet": ["腹部"],
			"defaultQuantity": {
				"gpQuantity": 6,
				"quantity": 10,
				"weight": 0
			},
			"selected": false,
			"gpMeasurement": "次",
			"measurement": "Kg"
		},
		{
			"id": 2,
			"name": "屈膝卷腹",
			"equipment": "",
			"description": "",
			"imageUrl": "image/actions/abs/bent_leg_crunch.png",
			"predefined": true,
			"partSet": ["腹部"],
			"defaultQuantity": {
				"gpQuantity": 6,
				"quantity": 10,
				"weight": 0
			},
			"selected": false,
			"gpMeasurement": "次",
			"measurement": "Kg"
		},
		{
			"id": 3,
			"name": "反向卷腹",
			"equipment": "",
			"description": "",
			"imageUrl": "image/actions/abs/reverse_crunch.png",
			"predefined": true,
			"partSet": ["腹部"],
			"defaultQuantity": {
				"gpQuantity": 6,
				"quantity": 10,
				"weight": 0
			},
			"selected": false,
			"gpMeasurement": "次",
			"measurement": "Kg"
		},
		{
			"id": 4,
			"name": "器械卷腹",
			"equipment": "",
			"description": "",
			"imageUrl": "image/actions/abs/machine_crunch.png",
			"predefined": true,
			"partSet": ["腹部"],
			"defaultQuantity": {
				"gpQuantity": 6,
				"quantity": 10,
				"weight": 10
			},
			"selected": false,
			"gpMeasurement": "次",
			"measurement": "Kg"
		},
		{
			"id": 5,
			"name": "悬垂卷腹",
			"equipment": "",
			"description": "",
			"imageUrl": "image/actions/abs/hanging_crunch.png",
			"predefined": true,
			"partSet": ["腹部"],
			"defaultQuantity": {
				"gpQuantity": 6,
				"quantity": 10,
				"weight": 0
			},
			"selected": false,
			"gpMeasurement": "次",
			"measurement": "Kg"
		},
		{
			"id": 6,
			"name": "悬垂举腿",
			"equipment": "",
			"description": "",
			"imageUrl": "image/actions/abs/hanging_leg_raise.png",
			"predefined": true,
			"partSet": ["腹部"],
			"defaultQuantity": {
				"gpQuantity": 6,
				"quantity": 10,
				"weight": 0
			},
			"selected": false,
			"gpMeasurement": "次",
			"measurement": "Kg"
		},
		{
			"id": 7,
			"name": "负重俄罗斯转体",
			"equipment": "",
			"description": "",
			"imageUrl": "image/actions/abs/weighted_russian_twist.png",
			"predefined": true,
			"partSet": ["腹部"],
			"defaultQuantity": {
				"gpQuantity": 6,
				"quantity": 10,
				"weight": 20
			},
			"selected": false,
			"gpMeasurement": "次",
			"measurement": "Kg"
		},
		{
			"id": 8,
			"name": "空中单车",
			"equipment": "",
			"description": "",
			"imageUrl": "image/actions/abs/sky_bike.png",
			"predefined": true,
			"partSet": ["腹部"],
			"defaultQuantity": {
				"gpQuantity": 6,
				"quantity": 10,
				"weight": 0
			},
			"selected": false,
			"gpMeasurement": "次",
			"measurement": "Kg"
		},
		{
			"id": 9,
			"name": "自重臀桥",
			"equipment": "",
			"description": "",
			"imageUrl": "image/actions/abs/self_weighted_hip_bridge.png",
			"predefined": true,
			"partSet": ["腹部"],
			"defaultQuantity": {
				"gpQuantity": 6,
				"quantity": 10,
				"weight": 0
			},
			"selected": false,
			"gpMeasurement": "次",
			"measurement": "Kg"
		},
		{
			"id": 10,
			"name": "平板支撑",
			"equipment": "",
			"description": "",
			"imageUrl": "image/actions/abs/plank.png",
			"predefined": true,
			"partSet": ["腹部"],
			"defaultQuantity": {
				"gpQuantity": 6,
				"quantity": 10,
				"weight": 0
			},
			"selected": false,
			"gpMeasurement": "次",
			"measurement": "Kg"
		},
		{
			"id": 11,
			"name": "V型平衡",
			"equipment": "",
			"description": "",
			"imageUrl": "image/actions/abs/v_balance.png",
			"predefined": true,
			"partSet": ["腹部"],
			"defaultQuantity": {
				"gpQuantity": 6,
				"quantity": 10,
				"weight": 0
			},
			"selected": false,
			"gpMeasurement": "次",
			"measurement": "Kg"
		},
		{
			"id": 12,
			"name": "自定义动作",
			"equipment": "",
			"description": "",
			"imageUrl": "image/plus_64px1.png",
			"predefined": true,
			"partSet": ["腹部"],
			"defaultQuantity": {
				
			},
			"selected": false
		}],
		"selected": false
	},
	{
		"id": 12,
		"bodyPart": "手臂",
		"name": "肱二头",
		"imageUrl": "image/bodyparts/arm.png",
		"description": "",
		"predefined": true,
		"actionSet": [{
			"id": 1,
			"name": "站姿杠铃弯举",
			"equipment": "",
			"description": "",
			"imageUrl": "image/actions/arm/standing_barbell_biceps_curl.png",
			"predefined": true,
			"partSet": ["手臂"],
			"defaultQuantity": {
				"gpQuantity": 6,
				"quantity": 10,
				"weight": 10
			},
			"selected": false,
			"gpMeasurement": "次",
			"measurement": "Kg"
		},
		{
			"id": 2,
			"name": "站姿重锤弯举",
			"equipment": "",
			"description": "",
			"imageUrl": "image/actions/arm/standing_hammer_curl.png",
			"predefined": true,
			"partSet": ["手臂"],
			"defaultQuantity": {
				"gpQuantity": 6,
				"quantity": 10,
				"weight": 10
			},
			"selected": false,
			"gpMeasurement": "次",
			"measurement": "Kg"
		},
		{
			"id": 3,
			"name": "坐姿哑铃集中弯举",
			"equipment": "",
			"description": "",
			"imageUrl": "image/actions/arm/seated_dumbbell_focus_curl.png",
			"predefined": true,
			"partSet": ["手臂"],
			"defaultQuantity": {
				"gpQuantity": 6,
				"quantity": 10,
				"weight": 10
			},
			"selected": false,
			"gpMeasurement": "次",
			"measurement": "Kg"
		},
		{
			"id": 4,
			"name": "坐姿重锤弯举",
			"equipment": "",
			"description": "",
			"imageUrl": "image/actions/arm/seated_hammer_curl.png",
			"predefined": true,
			"partSet": ["手臂"],
			"defaultQuantity": {
				"gpQuantity": 6,
				"quantity": 10,
				"weight": 10
			},
			"selected": false,
			"gpMeasurement": "次",
			"measurement": "Kg"
		},
		{
			"id": 5,
			"name": "坐姿哑铃弯举",
			"equipment": "",
			"description": "",
			"imageUrl": "image/actions/arm/seated_dumbbell_biceps_curl.png",
			"predefined": true,
			"partSet": ["手臂"],
			"defaultQuantity": {
				"gpQuantity": 6,
				"quantity": 10,
				"weight": 10
			},
			"selected": false,
			"gpMeasurement": "次",
			"measurement": "Kg"
		},
		{
			"id": 6,
			"name": "托板哑铃弯举",
			"equipment": "",
			"description": "",
			"imageUrl": "image/actions/arm/incline_dumbbell_curl.png",
			"predefined": true,
			"partSet": ["手臂"],
			"defaultQuantity": {
				"gpQuantity": 6,
				"quantity": 10,
				"weight": 20
			},
			"selected": false,
			"gpMeasurement": "次",
			"measurement": "Kg"
		},
		{
			"id": 7,
			"name": "站姿拉索弯举",
			"equipment": "",
			"description": "",
			"imageUrl": "image/actions/arm/standing_cable_curl.png",
			"predefined": true,
			"partSet": ["手臂"],
			"defaultQuantity": {
				"gpQuantity": 6,
				"quantity": 10,
				"weight": 10
			},
			"selected": false,
			"gpMeasurement": "次",
			"measurement": "Kg"
		}],
		"selected": false
	},
	{
		"id": 13,
		"bodyPart": "手臂",
		"name": "肱三头",
		"imageUrl": "image/bodyparts/arm.png",
		"description": "",
		"predefined": true,
		"actionSet": [{
			"id": 1,
			"name": "仰卧杠铃颈后臂屈伸",
			"equipment": "",
			"description": "",
			"imageUrl": "image/actions/arm/lying_barbell_dip.png",
			"predefined": true,
			"partSet": ["手臂"],
			"defaultQuantity": {
				"gpQuantity": 6,
				"quantity": 10,
				"weight": 20
			},
			"selected": false,
			"gpMeasurement": "次",
			"measurement": "Kg"
		},
		{
			"id": 2,
			"name": "站姿单臂颈后臂屈伸",
			"equipment": "",
			"description": "",
			"imageUrl": "image/actions/arm/standing_one_arm_dip.png",
			"predefined": true,
			"partSet": ["手臂"],
			"defaultQuantity": {
				"gpQuantity": 6,
				"quantity": 10,
				"weight": 10
			},
			"selected": false,
			"gpMeasurement": "次",
			"measurement": "Kg"
		},
		{
			"id": 3,
			"name": "站姿哑铃颈后屈臂伸",
			"equipment": "",
			"description": "",
			"imageUrl": "image/actions/arm/standing_dumbbell_dip.png",
			"predefined": true,
			"partSet": ["手臂"],
			"defaultQuantity": {
				"gpQuantity": 6,
				"quantity": 10,
				"weight": 20
			},
			"selected": false,
			"gpMeasurement": "次",
			"measurement": "Kg"
		},
		{
			"id": 4,
			"name": "站姿拉索下压",
			"equipment": "",
			"description": "",
			"imageUrl": "image/actions/arm/standing_cable_triceps_push_down.png",
			"predefined": true,
			"partSet": ["手臂"],
			"defaultQuantity": {
				"gpQuantity": 6,
				"quantity": 10,
				"weight": 10
			},
			"selected": false,
			"gpMeasurement": "次",
			"measurement": "Kg"
		},
		{
			"id": 5,
			"name": "双杠臂屈伸",
			"equipment": "",
			"description": "",
			"imageUrl": "image/actions/arm/parallel_bar_dip.png",
			"predefined": true,
			"partSet": ["手臂"],
			"defaultQuantity": {
				"gpQuantity": 6,
				"quantity": 10,
				"weight": 0
			},
			"selected": false,
			"gpMeasurement": "次",
			"measurement": "Kg"
		},
		{
			"id": 6,
			"name": "器械直臂下压",
			"equipment": "",
			"description": "",
			"imageUrl": "image/actions/arm/machine_push_down.png",
			"predefined": true,
			"partSet": ["手臂"],
			"defaultQuantity": {
				"gpQuantity": 6,
				"quantity": 10,
				"weight": 10
			},
			"selected": false,
			"gpMeasurement": "次",
			"measurement": "Kg"
		},
		{
			"id": 7,
			"name": "器械臂屈伸",
			"equipment": "",
			"description": "",
			"imageUrl": "image/actions/arm/machine_dip.png",
			"predefined": true,
			"partSet": ["手臂"],
			"defaultQuantity": {
				"gpQuantity": 6,
				"quantity": 10,
				"weight": 10
			},
			"selected": false,
			"gpMeasurement": "次",
			"measurement": "Kg"
		},
		{
			"id": 8,
			"name": "标准俯卧撑",
			"equipment": "",
			"description": "",
			"imageUrl": "image/actions/arm/standard_push_up.png",
			"predefined": true,
			"partSet": ["手臂"],
			"defaultQuantity": {
				"gpQuantity": 6,
				"quantity": 10,
				"weight": 0
			},
			"selected": false,
			"gpMeasurement": "次",
			"measurement": "Kg"
		},
		{
			"id": 9,
			"name": "钻石俯卧撑",
			"equipment": "",
			"description": "",
			"imageUrl": "image/actions/arm/diamond_push_up.png",
			"predefined": true,
			"partSet": ["手臂"],
			"defaultQuantity": {
				"gpQuantity": 6,
				"quantity": 10,
				"weight": 0
			},
			"selected": false,
			"gpMeasurement": "次",
			"measurement": "Kg"
		}],
		"selected": false
	},
	{
		"id": 14,
		"bodyPart": "手臂",
		"name": "小臂",
		"imageUrl": "image/bodyparts/arm.png",
		"description": "",
		"predefined": true,
		"actionSet": [{
			"id": 1,
			"name": "卷重物",
			"equipment": "",
			"description": "",
			"predefined": true,
			"partSet": ["手臂"],
			"defaultQuantity": {
				"gpQuantity": 6,
				"quantity": 10,
				"weight": 10
			},
			"selected": false,
			"gpMeasurement": "次",
			"measurement": "Kg"
		},
		{
			"id": 2,
			"name": "哑铃腕弯举",
			"equipment": "",
			"description": "",
			"predefined": true,
			"partSet": ["手臂"],
			"defaultQuantity": {
				"gpQuantity": 6,
				"quantity": 10,
				"weight": 10
			},
			"selected": false,
			"gpMeasurement": "次",
			"measurement": "Kg"
		},
		{
			"id": 3,
			"name": "杠铃背后腕腕举",
			"equipment": "",
			"description": "",
			"predefined": true,
			"partSet": ["手臂"],
			"defaultQuantity": {
				"gpQuantity": 6,
				"quantity": 10,
				"weight": 10
			},
			"selected": false,
			"gpMeasurement": "次",
			"measurement": "Kg"
		},
		{
			"id": 4,
			"name": "杠铃腕弯举",
			"equipment": "",
			"description": "",
			"predefined": true,
			"partSet": ["手臂"],
			"defaultQuantity": {
				"gpQuantity": 6,
				"quantity": 10,
				"weight": 10
			},
			"selected": false,
			"gpMeasurement": "次",
			"measurement": "Kg"
		},
		{
			"id": 5,
			"name": "引体悬挂",
			"equipment": "",
			"description": "",
			"predefined": true,
			"partSet": ["手臂"],
			"defaultQuantity": {
				"gpQuantity": 6,
				"quantity": 10,
				"weight": 0
			},
			"selected": false,
			"gpMeasurement": "次",
			"measurement": "Kg"
		},
		{
			"id": 6,
			"name": "自定义动作",
			"equipment": "",
			"description": "",
			"imageUrl": "image/plus_64px1.png",
			"predefined": true,
			"partSet": ["手臂"],
			"defaultQuantity": {
				
			},
			"selected": false
		}],
		"selected": false
	},
	{
		"id": 15,
		"bodyPart": "腿部",
		"name": "股二头",
		"imageUrl": "image/bodyparts/legs.png",
		"description": "",
		"predefined": true,
		"actionSet": [{
			"id": 1,
			"name": "俯卧器械腿弯举",
			"equipment": "",
			"description": "",
			"imageUrl": "image/actions/leg/bent_over_machine_leg_curl.png",
			"predefined": true,
			"partSet": ["腿部"],
			"defaultQuantity": {
				"gpQuantity": 6,
				"quantity": 10,
				"weight": 30
			},
			"selected": false,
			"gpMeasurement": "次",
			"measurement": "Kg"
		},
		{
			"id": 2,
			"name": "器械腿后展",
			"equipment": "",
			"description": "",
			"imageUrl": "image/actions/leg/cable_hamstring_curl.png",
			"predefined": true,
			"partSet": ["腿部"],
			"defaultQuantity": {
				"gpQuantity": 6,
				"quantity": 10,
				"weight": 30
			},
			"selected": false,
			"gpMeasurement": "次",
			"measurement": "Kg"
		}],
		"selected": false
	},
	{
		"id": 16,
		"bodyPart": "腿部",
		"name": "股四头",
		"imageUrl": "image/bodyparts/legs.png",
		"description": "",
		"predefined": true,
		"actionSet": [{
			"id": 1,
			"name": "杠铃深蹲",
			"equipment": "",
			"description": "",
			"imageUrl": "image/actions/leg/barbell_overhead_squat.png",
			"predefined": true,
			"partSet": ["腿部"],
			"defaultQuantity": {
				"gpQuantity": 6,
				"quantity": 10,
				"weight": 50
			},
			"selected": false,
			"gpMeasurement": "次",
			"measurement": "Kg"
		},
		{
			"id": 2,
			"name": "颈前杠铃深蹲",
			"equipment": "",
			"description": "",
			"imageUrl": "image/actions/leg/barbell_before_neck_squat.png",
			"predefined": true,
			"partSet": ["腿部"],
			"defaultQuantity": {
				"gpQuantity": 6,
				"quantity": 10,
				"weight": 30
			},
			"selected": false,
			"gpMeasurement": "次",
			"measurement": "Kg"
		},
		{
			"id": 3,
			"name": "器械哈克深蹲",
			"equipment": "",
			"description": "",
			"imageUrl": "image/actions/leg/machine_hack_squat.png",
			"predefined": true,
			"partSet": ["腿部"],
			"defaultQuantity": {
				"gpQuantity": 6,
				"quantity": 10,
				"weight": 50
			},
			"selected": false,
			"gpMeasurement": "次",
			"measurement": "Kg"
		},
		{
			"id": 4,
			"name": "哑铃深蹲",
			"equipment": "",
			"description": "",
			"imageUrl": "image/actions/leg/dumbbell_squat.png",
			"predefined": true,
			"partSet": ["腿部"],
			"defaultQuantity": {
				"gpQuantity": 6,
				"quantity": 10,
				"weight": 30
			},
			"selected": false,
			"gpMeasurement": "次",
			"measurement": "Kg"
		},
		{
			"id": 5,
			"name": "徒手深蹲",
			"equipment": "",
			"description": "",
			"imageUrl": "image/actions/leg/none_weighted_squat.png",
			"predefined": true,
			"partSet": ["腿部"],
			"defaultQuantity": {
				"gpQuantity": 6,
				"quantity": 10,
				"weight": 0
			},
			"selected": false,
			"gpMeasurement": "次",
			"measurement": "Kg"
		},
		{
			"id": 6,
			"name": "靠墙马步蹲",
			"equipment": "",
			"description": "",
			"imageUrl": "image/actions/leg/firm_stance.png",
			"predefined": true,
			"partSet": ["腿部"],
			"defaultQuantity": {
				"gpQuantity": 6,
				"quantity": 10,
				"weight": 0
			},
			"selected": false,
			"gpMeasurement": "次",
			"measurement": "Kg"
		},
		{
			"id": 7,
			"name": "器械腿举",
			"equipment": "",
			"description": "",
			"imageUrl": "image/actions/leg/machine_leg_lift.png",
			"predefined": true,
			"partSet": ["腿部"],
			"defaultQuantity": {
				"gpQuantity": 6,
				"quantity": 10,
				"weight": 40
			},
			"selected": false,
			"gpMeasurement": "次",
			"measurement": "Kg"
		},
		{
			"id": 8,
			"name": "坐姿单腿腿举",
			"equipment": "",
			"description": "",
			"imageUrl": "image/actions/leg/seated_one_leg_lift.png",
			"predefined": true,
			"partSet": ["腿部"],
			"defaultQuantity": {
				"gpQuantity": 6,
				"quantity": 10,
				"weight": 20
			},
			"selected": false,
			"gpMeasurement": "次",
			"measurement": "Kg"
		},
		{
			"id": 9,
			"name": "杠铃翘臀分腿蹲",
			"equipment": "",
			"description": "",
			"imageUrl": "image/actions/leg/barbell_one_leg_squat.png",
			"predefined": true,
			"partSet": ["腿部"],
			"defaultQuantity": {
				"gpQuantity": 6,
				"quantity": 10,
				"weight": 30
			},
			"selected": false,
			"gpMeasurement": "次",
			"measurement": "Kg"
		},
		{
			"id": 10,
			"name": "坐姿腿屈伸",
			"equipment": "",
			"description": "",
			"imageUrl": "image/actions/leg/seated_leg_dip.png",
			"predefined": true,
			"partSet": ["腿部"],
			"defaultQuantity": {
				"gpQuantity": 6,
				"quantity": 10,
				"weight": 20
			},
			"selected": false,
			"gpMeasurement": "次",
			"measurement": "Kg"
		},
		{
			"id": 11,
			"name": "坐姿器械腿外展",
			"equipment": "",
			"description": "",
			"imageUrl": "image/actions/leg/seated_machine_leg_split.png",
			"predefined": true,
			"partSet": ["腿部"],
			"defaultQuantity": {
				"gpQuantity": 6,
				"quantity": 10,
				"weight": 20
			},
			"selected": false,
			"gpMeasurement": "次",
			"measurement": "Kg"
		}],
		"selected": false
	},
	{
		"id": 17,
		"bodyPart": "腿部",
		"name": "小腿",
		"imageUrl": "image/bodyparts/legs.png",
		"description": "",
		"predefined": true,
		"actionSet": [{
			"id": 1,
			"name": "站姿负重提踵",
			"equipment": "",
			"description": "",
			"imageUrl": "image/actions/leg/standing_calf_raise.png",
			"predefined": true,
			"partSet": ["腿部"],
			"defaultQuantity": {
				"gpQuantity": 6,
				"quantity": 10,
				"weight": 40
			},
			"selected": false,
			"gpMeasurement": "次",
			"measurement": "Kg"
		},
		{
			"id": 2,
			"name": "坐姿提踵",
			"equipment": "",
			"description": "",
			"imageUrl": "image/actions/leg/seated_calf_raise.png",
			"predefined": true,
			"partSet": ["腿部"],
			"defaultQuantity": {
				"gpQuantity": 6,
				"quantity": 10,
				"weight": 40
			},
			"selected": false,
			"gpMeasurement": "次",
			"measurement": "Kg"
		}],
		"selected": false
	}]
}